{"IFS.findingaid":{"type":"SpecDataFindingAid",
"subtype":"Unknown",
"id":"0",
"created":"19 Jun 2021 04:08:53 GMT",
"pubInfo":{"authors":"Romeo, Joseph R., McDermott, Luca, Bennett, Clay S.",
"title":"Reagent-Controlled \u03b1-Selective Dehydrative Glycosylation of 2,6-Dideoxy Sugars: Construction of the Arugomycin Tetrasaccharide",
"desc":"Organic Letters, 22(9), 3649-3654",
"uri":"https://doi.org/10.1021/acs.orglett.0c01153"},
"urls":["https://ndownloader.figshare.com/files/22284726",
"https://ndownloader.figshare.com/files/22284729"],
"params":{"IFS.fairspec.data.license.name":"cc-by-nc-4.0",
"IFS.fairspec.data.license.uri":"https://creativecommons.org/licenses/by-nc/4.0"},
"structuresCount":20,
"structures":{"type":"StructureCollection",
"subtype":"Unknown",
"id":"1",
"listCount":20,
"list":[{"type":"Structure",
"subtype":"Unknown",
"name":"Compound 10",
"id":"0",
"urlIndex":0,
"path":"22284726",
"params":{"IFS.structure.param.compound.id":"Compound 10"},
"listCount":1,
"list":[{"type":"chemical/x-cdx (ChemDraw CDX)",
"len":3102,
"ref":{"path":"22284726",
"localName":"Compound_10.zip_Compound_10_Compound_10.cdx",
"value":"./22284726"}}]},
{"type":"Structure",
"subtype":"Unknown",
"name":"compound 5",
"id":"1",
"urlIndex":0,
"path":"22284726",
"params":{"IFS.structure.param.compound.id":"compound 5"},
"listCount":1,
"list":[{"type":"chemical/x-cdx (ChemDraw CDX)",
"len":4540,
"ref":{"path":"22284726",
"localName":"compound_5.zip_compound_5_Compound_5_copy.cdx",
"value":"./22284726"}}]},
{"type":"Structure",
"subtype":"Unknown",
"name":"Compound 4",
"id":"2",
"urlIndex":0,
"path":"22284726",
"params":{"IFS.structure.param.compound.id":"Compound 4"},
"listCount":1,
"list":[{"type":"chemical/x-cdx (ChemDraw CDX)",
"len":5048,
"ref":{"path":"22284726",
"localName":"Compound_4.zip_Compound_4_compound_4_copy.cdx",
"value":"./22284726"}}]},
{"type":"Structure",
"subtype":"Unknown",
"name":"compound 6",
"id":"3",
"urlIndex":0,
"path":"22284726",
"params":{"IFS.structure.param.compound.id":"compound 6"},
"listCount":1,
"list":[{"type":"chemical/x-cdx (ChemDraw CDX)",
"len":3301,
"ref":{"path":"22284726",
"localName":"compound_6.zip_compound_6_Compound_6_copy.cdx",
"value":"./22284726"}}]},
{"type":"Structure",
"subtype":"Unknown",
"name":"COmpound 7",
"id":"4",
"urlIndex":0,
"path":"22284726",
"params":{"IFS.structure.param.compound.id":"COmpound 7"},
"listCount":1,
"list":[{"type":"chemical/x-cdx (ChemDraw CDX)",
"len":3695,
"ref":{"path":"22284726",
"localName":"COmpound_7.zip_COmpound_7_Compound_7.cdx",
"value":"./22284726"}}]},
{"type":"Structure",
"subtype":"Unknown",
"name":"Compound 3",
"id":"5",
"urlIndex":0,
"path":"22284726",
"params":{"IFS.structure.param.compound.id":"Compound 3"},
"listCount":1,
"list":[{"type":"chemical/x-cdx (ChemDraw CDX)",
"len":8366,
"ref":{"path":"22284726",
"localName":"Compound_3.zip_Compound_3_Compound_3_copy.cdx",
"value":"./22284726"}}]},
{"type":"Structure",
"subtype":"Unknown",
"name":"compound 2",
"id":"6",
"urlIndex":0,
"path":"22284726",
"params":{"IFS.structure.param.compound.id":"compound 2"},
"listCount":1,
"list":[{"type":"chemical/x-cdx (ChemDraw CDX)",
"len":2493,
"ref":{"path":"22284726",
"localName":"compound_2.zip_compound_2_Compound_2.cdx",
"value":"./22284726"}}]},
{"type":"Structure",
"subtype":"Unknown",
"name":"Compound 1",
"id":"7",
"urlIndex":0,
"path":"22284726",
"params":{"IFS.structure.param.compound.id":"Compound 1"},
"listCount":1,
"list":[{"type":"chemical/x-cdx (ChemDraw CDX)",
"len":8190,
"ref":{"path":"22284726",
"localName":"Compound_1.zip_Compound_1_compound_1.cdx",
"value":"./22284726"}}]},
{"type":"Structure",
"subtype":"Unknown",
"name":"compound 9",
"id":"8",
"urlIndex":0,
"path":"22284726",
"params":{"IFS.structure.param.compound.id":"compound 9"},
"listCount":1,
"list":[{"type":"chemical/x-cdx (ChemDraw CDX)",
"len":4381,
"ref":{"path":"22284726",
"localName":"compound_9.zip_compound_9_Untitled_Document-25_copy.cdx",
"value":"./22284726"}}]},
{"type":"Structure",
"subtype":"Unknown",
"name":"compound 8",
"id":"9",
"urlIndex":0,
"path":"22284726",
"params":{"IFS.structure.param.compound.id":"compound 8"}},
{"type":"Structure",
"subtype":"Unknown",
"name":"Compound s3",
"id":"10",
"urlIndex":1,
"path":"22284729",
"params":{"IFS.structure.param.compound.id":"Compound s3"},
"listCount":1,
"list":[{"type":"chemical/x-cdx (ChemDraw CDX)",
"len":6184,
"ref":{"path":"22284729",
"localName":"Compound_s3.zip_Compound_s3_Compound_S3_copy.cdx",
"value":"./22284729"}}]},
{"type":"Structure",
"subtype":"Unknown",
"name":"Compound 11",
"id":"11",
"urlIndex":1,
"path":"22284729",
"params":{"IFS.structure.param.compound.id":"Compound 11"},
"listCount":1,
"list":[{"type":"chemical/x-cdx (ChemDraw CDX)",
"len":6213,
"ref":{"path":"22284729",
"localName":"Compound_11.zip_Compound_11_COmpound_11_copy.cdx",
"value":"./22284729"}}]},
{"type":"Structure",
"subtype":"Unknown",
"name":"Compound 12",
"id":"12",
"urlIndex":1,
"path":"22284729",
"params":{"IFS.structure.param.compound.id":"Compound 12"},
"listCount":1,
"list":[{"type":"chemical/x-cdx (ChemDraw CDX)",
"len":2885,
"ref":{"path":"22284729",
"localName":"Compound_12.zip_Compound_12_Untitled_Document-28_copy.cdx",
"value":"./22284729"}}]},
{"type":"Structure",
"subtype":"Unknown",
"name":"Compound 13",
"id":"13",
"urlIndex":1,
"path":"22284729",
"params":{"IFS.structure.param.compound.id":"Compound 13"},
"listCount":1,
"list":[{"type":"chemical/x-cdx (ChemDraw CDX)",
"len":3990,
"ref":{"path":"22284729",
"localName":"Compound_13.zip_Compound_13_compound_13_copy.cdx",
"value":"./22284729"}}]},
{"type":"Structure",
"subtype":"Unknown",
"name":"compound s5",
"id":"14",
"urlIndex":1,
"path":"22284729",
"params":{"IFS.structure.param.compound.id":"compound s5"},
"listCount":1,
"list":[{"type":"chemical/x-cdx (ChemDraw CDX)",
"len":3131,
"ref":{"path":"22284729",
"localName":"compound_s5.zip_compound_s5_Compound_s5_copy.cdx",
"value":"./22284729"}}]},
{"type":"Structure",
"subtype":"Unknown",
"name":"Compound 17",
"id":"15",
"urlIndex":1,
"path":"22284729",
"params":{"IFS.structure.param.compound.id":"Compound 17"},
"listCount":1,
"list":[{"type":"chemical/x-cdx (ChemDraw CDX)",
"len":8893,
"ref":{"path":"22284729",
"localName":"Compound_17.zip_Compound_17_Compound_17_copy.cdx",
"value":"./22284729"}}]},
{"type":"Structure",
"subtype":"Unknown",
"name":"Compound 16",
"id":"16",
"urlIndex":1,
"path":"22284729",
"params":{"IFS.structure.param.compound.id":"Compound 16"},
"listCount":1,
"list":[{"type":"chemical/x-cdx (ChemDraw CDX)",
"len":5737,
"ref":{"path":"22284729",
"localName":"Compound_16.zip_Compound_16_Compound_16_copy.cdx",
"value":"./22284729"}}]},
{"type":"Structure",
"subtype":"Unknown",
"name":"Compound 14",
"id":"17",
"urlIndex":1,
"path":"22284729",
"params":{"IFS.structure.param.compound.id":"Compound 14"},
"listCount":1,
"list":[{"type":"chemical/x-cdx (ChemDraw CDX)",
"len":6193,
"ref":{"path":"22284729",
"localName":"Compound_14.zip_Compound_14_Untitled_Document-30_copy.cdx",
"value":"./22284729"}}]},
{"type":"Structure",
"subtype":"Unknown",
"name":"Compound 15",
"id":"18",
"urlIndex":1,
"path":"22284729",
"params":{"IFS.structure.param.compound.id":"Compound 15"},
"listCount":1,
"list":[{"type":"chemical/x-cdx (ChemDraw CDX)",
"len":5286,
"ref":{"path":"22284729",
"localName":"Compound_15.zip_Compound_15_Compound_15_copy.cdx",
"value":"./22284729"}}]},
{"type":"Structure",
"subtype":"Unknown",
"name":"compound s8",
"id":"19",
"urlIndex":1,
"path":"22284729",
"params":{"IFS.structure.param.compound.id":"compound s8"},
"listCount":1,
"list":[{"type":"chemical/x-cdx (ChemDraw CDX)",
"len":7677,
"ref":{"path":"22284729",
"localName":"compound_s8.zip_compound_s8_Compound_S8_copy.cdx",
"value":"./22284729"}}]}]},
"specDataCount":64,
"specData":{"type":"SpecDataCollection",
"subtype":"NMRSpecData",
"id":"3",
"listCount":64,
"list":[{"type":"NMRSpecData",
"subtype":"Unknown",
"name":"1H.zip|1H/",
"id":"0",
"urlIndex":0,
"path":"22284726",
"params":{"IFS.spec.nmr.param.expt":"1H",
"IFS.spec.nmr.expt.dim":"1D",
"IFS.spec.nmr.nucl.1":"1H",
"IFS.spec.nmr.expt.pulseprog":"zg30",
"IFS.spec.nmr.freq.nominal":500},
"listCount":1,
"list":[{"type":"unknown",
"len":580791,
"ref":{"path":"22284726",
"localName":"Compound_10.zip_Compound_10_1H.zip_1H_.zip",
"value":"Compound_10.zip|Compound 10/1H.zip|1H/"}}]},
{"type":"NMRSpecData",
"subtype":"Unknown",
"name":"13C.zip|13C/",
"id":"1",
"urlIndex":0,
"path":"22284726",
"params":{"IFS.spec.nmr.param.expt":"13C",
"IFS.spec.nmr.expt.dim":"1D",
"IFS.spec.nmr.nucl.1":"13C",
"IFS.spec.nmr.expt.pulseprog":"zgpg30",
"IFS.spec.nmr.freq.nominal":500},
"listCount":1,
"list":[{"type":"unknown",
"len":638977,
"ref":{"path":"22284726",
"localName":"Compound_10.zip_Compound_10_13C.zip_13C_.zip",
"value":"Compound_10.zip|Compound 10/13C.zip|13C/"}}]},
{"type":"NMRSpecData",
"subtype":"Unknown",
"name":"1H.zip|1H/",
"id":"2",
"urlIndex":0,
"path":"22284726",
"params":{"IFS.spec.nmr.param.expt":"1H",
"IFS.spec.nmr.expt.dim":"1D",
"IFS.spec.nmr.nucl.1":"1H",
"IFS.spec.nmr.expt.pulseprog":"zgpr",
"IFS.spec.nmr.freq.nominal":500},
"listCount":1,
"list":[{"type":"unknown",
"len":224682,
"ref":{"path":"22284726",
"localName":"compound_5.zip_compound_5_1H.zip_1H_.zip",
"value":"compound_5.zip|compound 5/1H.zip|1H/"}}]},
{"type":"NMRSpecData",
"subtype":"Unknown",
"name":"13C.zip|13C/",
"id":"3",
"urlIndex":0,
"path":"22284726",
"params":{"IFS.spec.nmr.param.expt":"13C",
"IFS.spec.nmr.expt.dim":"1D",
"IFS.spec.nmr.nucl.1":"13C",
"IFS.spec.nmr.expt.pulseprog":"zgpg",
"IFS.spec.nmr.freq.nominal":500},
"listCount":1,
"list":[{"type":"unknown",
"len":643572,
"ref":{"path":"22284726",
"localName":"compound_5.zip_compound_5_13C.zip_13C_.zip",
"value":"compound_5.zip|compound 5/13C.zip|13C/"}}]},
{"type":"NMRSpecData",
"subtype":"Unknown",
"name":"HSQC.zip|HSQC/",
"id":"4",
"urlIndex":0,
"path":"22284726",
"params":{"IFS.spec.nmr.param.expt":"HSQC",
"IFS.spec.nmr.expt.dim":"2D",
"IFS.spec.nmr.nucl.2":"13C",
"IFS.spec.nmr.nucl.1":"1H",
"IFS.spec.nmr.expt.pulseprog":"hsqcetgp",
"IFS.spec.nmr.freq.nominal":500},
"listCount":1,
"list":[{"type":"unknown",
"len":15276045,
"ref":{"path":"22284726",
"localName":"compound_5.zip_compound_5_HSQC.zip_HSQC_.zip",
"value":"compound_5.zip|compound 5/HSQC.zip|HSQC/"}}]},
{"type":"NMRSpecData",
"subtype":"Unknown",
"name":"COSY.zip|COSY/",
"id":"5",
"urlIndex":0,
"path":"22284726",
"params":{"IFS.spec.nmr.param.expt":"COSY",
"IFS.spec.nmr.expt.dim":"2D",
"IFS.spec.nmr.nucl.1":"1H",
"IFS.spec.nmr.expt.pulseprog":"cosygpqf",
"IFS.spec.nmr.freq.nominal":500},
"listCount":1,
"list":[{"type":"unknown",
"len":3681701,
"ref":{"path":"22284726",
"localName":"compound_5.zip_compound_5_COSY.zip_COSY_.zip",
"value":"compound_5.zip|compound 5/COSY.zip|COSY/"}}]},
{"type":"NMRSpecData",
"subtype":"Unknown",
"name":"1H.zip|1H/",
"id":"6",
"urlIndex":0,
"path":"22284726",
"params":{"IFS.spec.nmr.param.expt":"1H",
"IFS.spec.nmr.expt.dim":"1D",
"IFS.spec.nmr.nucl.1":"1H",
"IFS.spec.nmr.expt.pulseprog":"zg30",
"IFS.spec.nmr.freq.nominal":500},
"listCount":1,
"list":[{"type":"unknown",
"len":583845,
"ref":{"path":"22284726",
"localName":"Compound_4.zip_Compound_4_1H.zip_1H_.zip",
"value":"Compound_4.zip|Compound 4/1H.zip|1H/"}}]},
{"type":"NMRSpecData",
"subtype":"Unknown",
"name":"13C.zip|13C/",
"id":"7",
"urlIndex":0,
"path":"22284726",
"params":{"IFS.spec.nmr.param.expt":"13C",
"IFS.spec.nmr.expt.dim":"1D",
"IFS.spec.nmr.nucl.1":"13C",
"IFS.spec.nmr.expt.pulseprog":"zgpg30",
"IFS.spec.nmr.freq.nominal":500},
"listCount":1,
"list":[{"type":"unknown",
"len":643754,
"ref":{"path":"22284726",
"localName":"Compound_4.zip_Compound_4_13C.zip_13C_.zip",
"value":"Compound_4.zip|Compound 4/13C.zip|13C/"}}]},
{"type":"NMRSpecData",
"subtype":"Unknown",
"name":"HSQC.zip|HSQC/",
"id":"8",
"urlIndex":0,
"path":"22284726",
"params":{"IFS.spec.nmr.param.expt":"HSQC",
"IFS.spec.nmr.expt.dim":"2D",
"IFS.spec.nmr.nucl.2":"13C",
"IFS.spec.nmr.nucl.1":"1H",
"IFS.spec.nmr.expt.pulseprog":"hsqcetgp",
"IFS.spec.nmr.freq.nominal":500},
"listCount":1,
"list":[{"type":"unknown",
"len":14547355,
"ref":{"path":"22284726",
"localName":"Compound_4.zip_Compound_4_HSQC.zip_HSQC_.zip",
"value":"Compound_4.zip|Compound 4/HSQC.zip|HSQC/"}}]},
{"type":"NMRSpecData",
"subtype":"Unknown",
"name":"COSY.zip|COSY/",
"id":"9",
"urlIndex":0,
"path":"22284726",
"params":{"IFS.spec.nmr.param.expt":"COSY",
"IFS.spec.nmr.expt.dim":"2D",
"IFS.spec.nmr.nucl.1":"1H",
"IFS.spec.nmr.expt.pulseprog":"cosygpqf",
"IFS.spec.nmr.freq.nominal":500},
"listCount":1,
"list":[{"type":"unknown",
"len":3382949,
"ref":{"path":"22284726",
"localName":"Compound_4.zip_Compound_4_COSY.zip_COSY_.zip",
"value":"Compound_4.zip|Compound 4/COSY.zip|COSY/"}}]},
{"type":"NMRSpecData",
"subtype":"Unknown",
"name":"1H.zip|1H/",
"id":"10",
"urlIndex":0,
"path":"22284726",
"params":{"IFS.spec.nmr.param.expt":"1H",
"IFS.spec.nmr.expt.dim":"1D",
"IFS.spec.nmr.nucl.1":"1H",
"IFS.spec.nmr.expt.pulseprog":"zg30",
"IFS.spec.nmr.freq.nominal":500},
"listCount":1,
"list":[{"type":"unknown",
"len":563364,
"ref":{"path":"22284726",
"localName":"compound_6.zip_compound_6_1H.zip_1H_.zip",
"value":"compound_6.zip|compound 6/1H.zip|1H/"}}]},
{"type":"NMRSpecData",
"subtype":"Unknown",
"name":"13C.zip|13C/",
"id":"11",
"urlIndex":0,
"path":"22284726",
"params":{"IFS.spec.nmr.param.expt":"13C",
"IFS.spec.nmr.expt.dim":"1D",
"IFS.spec.nmr.nucl.1":"13C",
"IFS.spec.nmr.expt.pulseprog":"zgpg30",
"IFS.spec.nmr.freq.nominal":500},
"listCount":1,
"list":[{"type":"unknown",
"len":630781,
"ref":{"path":"22284726",
"localName":"compound_6.zip_compound_6_13C.zip_13C_.zip",
"value":"compound_6.zip|compound 6/13C.zip|13C/"}}]},
{"type":"NMRSpecData",
"subtype":"Unknown",
"name":"HSQC.zip|HSQC/",
"id":"12",
"urlIndex":0,
"path":"22284726",
"params":{"IFS.spec.nmr.param.expt":"HSQC",
"IFS.spec.nmr.expt.dim":"2D",
"IFS.spec.nmr.nucl.2":"13C",
"IFS.spec.nmr.nucl.1":"1H",
"IFS.spec.nmr.expt.pulseprog":"hsqcetgp",
"IFS.spec.nmr.freq.nominal":500},
"listCount":1,
"list":[{"type":"unknown",
"len":15095082,
"ref":{"path":"22284726",
"localName":"compound_6.zip_compound_6_HSQC.zip_HSQC_.zip",
"value":"compound_6.zip|compound 6/HSQC.zip|HSQC/"}}]},
{"type":"NMRSpecData",
"subtype":"Unknown",
"name":"COSY.zip|COSY/",
"id":"13",
"urlIndex":0,
"path":"22284726",
"params":{"IFS.spec.nmr.param.expt":"COSY",
"IFS.spec.nmr.expt.dim":"2D",
"IFS.spec.nmr.nucl.1":"1H",
"IFS.spec.nmr.expt.pulseprog":"cosygpqf",
"IFS.spec.nmr.freq.nominal":500},
"listCount":1,
"list":[{"type":"unknown",
"len":3308679,
"ref":{"path":"22284726",
"localName":"compound_6.zip_compound_6_COSY.zip_COSY_.zip",
"value":"compound_6.zip|compound 6/COSY.zip|COSY/"}}]},
{"type":"NMRSpecData",
"subtype":"Unknown",
"name":"1H.zip|1H/",
"id":"14",
"urlIndex":0,
"path":"22284726",
"params":{"IFS.spec.nmr.param.expt":"1H",
"IFS.spec.nmr.expt.dim":"1D",
"IFS.spec.nmr.nucl.1":"1H",
"IFS.spec.nmr.expt.pulseprog":"zg30",
"IFS.spec.nmr.freq.nominal":500},
"listCount":1,
"list":[{"type":"unknown",
"len":548891,
"ref":{"path":"22284726",
"localName":"COmpound_7.zip_COmpound_7_1H.zip_1H_.zip",
"value":"COmpound_7.zip|COmpound 7/1H.zip|1H/"}}]},
{"type":"NMRSpecData",
"subtype":"Unknown",
"name":"13C.zip|13C/",
"id":"15",
"urlIndex":0,
"path":"22284726",
"params":{"IFS.spec.nmr.param.expt":"13C",
"IFS.spec.nmr.expt.dim":"1D",
"IFS.spec.nmr.nucl.1":"13C",
"IFS.spec.nmr.expt.pulseprog":"zgpg30",
"IFS.spec.nmr.freq.nominal":500},
"listCount":1,
"list":[{"type":"unknown",
"len":646096,
"ref":{"path":"22284726",
"localName":"COmpound_7.zip_COmpound_7_13C.zip_13C_.zip",
"value":"COmpound_7.zip|COmpound 7/13C.zip|13C/"}}]},
{"type":"NMRSpecData",
"subtype":"Unknown",
"name":"HSQC.zip|HSQC/",
"id":"16",
"urlIndex":0,
"path":"22284726",
"params":{"IFS.spec.nmr.param.expt":"HSQC",
"IFS.spec.nmr.expt.dim":"2D",
"IFS.spec.nmr.nucl.2":"13C",
"IFS.spec.nmr.nucl.1":"1H",
"IFS.spec.nmr.expt.pulseprog":"hsqcetgp",
"IFS.spec.nmr.freq.nominal":500},
"listCount":1,
"list":[{"type":"unknown",
"len":13680084,
"ref":{"path":"22284726",
"localName":"COmpound_7.zip_COmpound_7_HSQC.zip_HSQC_.zip",
"value":"COmpound_7.zip|COmpound 7/HSQC.zip|HSQC/"}}]},
{"type":"NMRSpecData",
"subtype":"Unknown",
"name":"COSY.zip|COSY/",
"id":"17",
"urlIndex":0,
"path":"22284726",
"params":{"IFS.spec.nmr.param.expt":"COSY",
"IFS.spec.nmr.expt.dim":"2D",
"IFS.spec.nmr.nucl.1":"1H",
"IFS.spec.nmr.expt.pulseprog":"cosygpqf",
"IFS.spec.nmr.freq.nominal":500},
"listCount":1,
"list":[{"type":"unknown",
"len":3223145,
"ref":{"path":"22284726",
"localName":"COmpound_7.zip_COmpound_7_COSY.zip_COSY_.zip",
"value":"COmpound_7.zip|COmpound 7/COSY.zip|COSY/"}}]},
{"type":"NMRSpecData",
"subtype":"Unknown",
"name":"1H.zip|1H/",
"id":"18",
"urlIndex":0,
"path":"22284726",
"params":{"IFS.spec.nmr.param.expt":"1H",
"IFS.spec.nmr.expt.dim":"1D",
"IFS.spec.nmr.nucl.1":"1H",
"IFS.spec.nmr.expt.pulseprog":"zg30",
"IFS.spec.nmr.freq.nominal":500},
"listCount":1,
"list":[{"type":"unknown",
"len":562958,
"ref":{"path":"22284726",
"localName":"Compound_3.zip_Compound_3_1H.zip_1H_.zip",
"value":"Compound_3.zip|Compound 3/1H.zip|1H/"}}]},
{"type":"NMRSpecData",
"subtype":"Unknown",
"name":"13C.zip|13C/",
"id":"19",
"urlIndex":0,
"path":"22284726",
"params":{"IFS.spec.nmr.param.expt":"13C",
"IFS.spec.nmr.expt.dim":"1D",
"IFS.spec.nmr.nucl.1":"13C",
"IFS.spec.nmr.expt.pulseprog":"zgpg30",
"IFS.spec.nmr.freq.nominal":500},
"listCount":1,
"list":[{"type":"unknown",
"len":607363,
"ref":{"path":"22284726",
"localName":"Compound_3.zip_Compound_3_13C.zip_13C_.zip",
"value":"Compound_3.zip|Compound 3/13C.zip|13C/"}}]},
{"type":"NMRSpecData",
"subtype":"Unknown",
"name":"HSQC.zip|HSQC/",
"id":"20",
"urlIndex":0,
"path":"22284726",
"params":{"IFS.spec.nmr.param.expt":"HSQC",
"IFS.spec.nmr.expt.dim":"2D",
"IFS.spec.nmr.nucl.2":"13C",
"IFS.spec.nmr.nucl.1":"1H",
"IFS.spec.nmr.expt.pulseprog":"hsqcetgp",
"IFS.spec.nmr.freq.nominal":500},
"listCount":1,
"list":[{"type":"unknown",
"len":14146122,
"ref":{"path":"22284726",
"localName":"Compound_3.zip_Compound_3_HSQC.zip_HSQC_.zip",
"value":"Compound_3.zip|Compound 3/HSQC.zip|HSQC/"}}]},
{"type":"NMRSpecData",
"subtype":"Unknown",
"name":"COSY.zip|COSY/",
"id":"21",
"urlIndex":0,
"path":"22284726",
"params":{"IFS.spec.nmr.param.expt":"COSY",
"IFS.spec.nmr.expt.dim":"2D",
"IFS.spec.nmr.nucl.1":"1H",
"IFS.spec.nmr.expt.pulseprog":"cosygpqf",
"IFS.spec.nmr.freq.nominal":500},
"listCount":1,
"list":[{"type":"unknown",
"len":3340768,
"ref":{"path":"22284726",
"localName":"Compound_3.zip_Compound_3_COSY.zip_COSY_.zip",
"value":"Compound_3.zip|Compound 3/COSY.zip|COSY/"}}]},
{"type":"NMRSpecData",
"subtype":"Unknown",
"name":"1H.zip|1H/",
"id":"22",
"urlIndex":0,
"path":"22284726",
"params":{"IFS.spec.nmr.param.expt":"1H",
"IFS.spec.nmr.expt.dim":"1D",
"IFS.spec.nmr.nucl.1":"1H",
"IFS.spec.nmr.expt.pulseprog":"zg30",
"IFS.spec.nmr.freq.nominal":500},
"listCount":1,
"list":[{"type":"unknown",
"len":512705,
"ref":{"path":"22284726",
"localName":"compound_2.zip_compound_2_1H.zip_1H_.zip",
"value":"compound_2.zip|compound 2/1H.zip|1H/"}}]},
{"type":"NMRSpecData",
"subtype":"Unknown",
"name":"13C.zip|13C/",
"id":"23",
"urlIndex":0,
"path":"22284726",
"params":{"IFS.spec.nmr.param.expt":"13C",
"IFS.spec.nmr.expt.dim":"1D",
"IFS.spec.nmr.nucl.1":"13C",
"IFS.spec.nmr.expt.pulseprog":"zgpg30",
"IFS.spec.nmr.freq.nominal":500},
"listCount":1,
"list":[{"type":"unknown",
"len":631472,
"ref":{"path":"22284726",
"localName":"compound_2.zip_compound_2_13C.zip_13C_.zip",
"value":"compound_2.zip|compound 2/13C.zip|13C/"}}]},
{"type":"NMRSpecData",
"subtype":"Unknown",
"name":"1H.zip|1H/",
"id":"24",
"urlIndex":0,
"path":"22284726",
"params":{"IFS.spec.nmr.param.expt":"1H",
"IFS.spec.nmr.expt.dim":"1D",
"IFS.spec.nmr.nucl.1":"1H",
"IFS.spec.nmr.expt.pulseprog":"zg30",
"IFS.spec.nmr.freq.nominal":500},
"listCount":1,
"list":[{"type":"unknown",
"len":559904,
"ref":{"path":"22284726",
"localName":"Compound_1.zip_Compound_1_1H.zip_1H_.zip",
"value":"Compound_1.zip|Compound 1/1H.zip|1H/"}}]},
{"type":"NMRSpecData",
"subtype":"Unknown",
"name":"13C.zip|13C/",
"id":"25",
"urlIndex":0,
"path":"22284726",
"params":{"IFS.spec.nmr.param.expt":"13C",
"IFS.spec.nmr.expt.dim":"1D",
"IFS.spec.nmr.nucl.1":"13C",
"IFS.spec.nmr.expt.pulseprog":"zgpg30",
"IFS.spec.nmr.freq.nominal":500},
"listCount":1,
"list":[{"type":"unknown",
"len":603814,
"ref":{"path":"22284726",
"localName":"Compound_1.zip_Compound_1_13C.zip_13C_.zip",
"value":"Compound_1.zip|Compound 1/13C.zip|13C/"}}]},
{"type":"NMRSpecData",
"subtype":"Unknown",
"name":"HSQC.zip|HSQC/",
"id":"26",
"urlIndex":0,
"path":"22284726",
"params":{"IFS.spec.nmr.param.expt":"HSQC",
"IFS.spec.nmr.expt.dim":"2D",
"IFS.spec.nmr.nucl.2":"13C",
"IFS.spec.nmr.nucl.1":"1H",
"IFS.spec.nmr.expt.pulseprog":"hsqcetgp",
"IFS.spec.nmr.freq.nominal":500},
"listCount":1,
"list":[{"type":"unknown",
"len":14902312,
"ref":{"path":"22284726",
"localName":"Compound_1.zip_Compound_1_HSQC.zip_HSQC_.zip",
"value":"Compound_1.zip|Compound 1/HSQC.zip|HSQC/"}}]},
{"type":"NMRSpecData",
"subtype":"Unknown",
"name":"COSY.zip|COSY/",
"id":"27",
"urlIndex":0,
"path":"22284726",
"params":{"IFS.spec.nmr.param.expt":"COSY",
"IFS.spec.nmr.expt.dim":"2D",
"IFS.spec.nmr.nucl.1":"1H",
"IFS.spec.nmr.expt.pulseprog":"cosygpqf",
"IFS.spec.nmr.freq.nominal":500},
"listCount":1,
"list":[{"type":"unknown",
"len":3535498,
"ref":{"path":"22284726",
"localName":"Compound_1.zip_Compound_1_COSY.zip_COSY_.zip",
"value":"Compound_1.zip|Compound 1/COSY.zip|COSY/"}}]},
{"type":"NMRSpecData",
"subtype":"Unknown",
"name":"1H.zip|1H/",
"id":"28",
"urlIndex":0,
"path":"22284726",
"params":{"IFS.spec.nmr.param.expt":"1H",
"IFS.spec.nmr.expt.dim":"1D",
"IFS.spec.nmr.nucl.1":"1H",
"IFS.spec.nmr.expt.pulseprog":"zg30",
"IFS.spec.nmr.freq.nominal":500},
"listCount":1,
"list":[{"type":"unknown",
"len":578059,
"ref":{"path":"22284726",
"localName":"compound_9.zip_compound_9_1H.zip_1H_.zip",
"value":"compound_9.zip|compound 9/1H.zip|1H/"}}]},
{"type":"NMRSpecData",
"subtype":"Unknown",
"name":"13C.zip|13C/",
"id":"29",
"urlIndex":0,
"path":"22284726",
"params":{"IFS.spec.nmr.param.expt":"13C",
"IFS.spec.nmr.expt.dim":"1D",
"IFS.spec.nmr.nucl.1":"13C",
"IFS.spec.nmr.expt.pulseprog":"zgpg30",
"IFS.spec.nmr.freq.nominal":500},
"listCount":1,
"list":[{"type":"unknown",
"len":638721,
"ref":{"path":"22284726",
"localName":"compound_9.zip_compound_9_13C.zip_13C_.zip",
"value":"compound_9.zip|compound 9/13C.zip|13C/"}}]},
{"type":"NMRSpecData",
"subtype":"Unknown",
"name":"1H.zip|1H/",
"id":"30",
"urlIndex":0,
"path":"22284726",
"params":{"IFS.spec.nmr.param.expt":"1H",
"IFS.spec.nmr.expt.dim":"1D",
"IFS.spec.nmr.nucl.1":"1H",
"IFS.spec.nmr.expt.pulseprog":"zg30",
"IFS.spec.nmr.freq.nominal":500},
"listCount":1,
"list":[{"type":"unknown",
"len":561246,
"ref":{"path":"22284726",
"localName":"compound_8.zip_compound_8_1H.zip_1H_.zip",
"value":"compound_8.zip|compound 8/1H.zip|1H/"}}]},
{"type":"NMRSpecData",
"subtype":"Unknown",
"name":"13C.zip|13C/",
"id":"31",
"urlIndex":0,
"path":"22284726",
"params":{"IFS.spec.nmr.param.expt":"13C",
"IFS.spec.nmr.expt.dim":"1D",
"IFS.spec.nmr.nucl.1":"13C",
"IFS.spec.nmr.expt.pulseprog":"zgpg30",
"IFS.spec.nmr.freq.nominal":500},
"listCount":1,
"list":[{"type":"unknown",
"len":643253,
"ref":{"path":"22284726",
"localName":"compound_8.zip_compound_8_13C.zip_13C_.zip",
"value":"compound_8.zip|compound 8/13C.zip|13C/"}}]},
{"type":"NMRSpecData",
"subtype":"Unknown",
"name":"HSQC.zip|HSQC/",
"id":"32",
"urlIndex":0,
"path":"22284726",
"params":{"IFS.spec.nmr.param.expt":"HSQC",
"IFS.spec.nmr.expt.dim":"2D",
"IFS.spec.nmr.nucl.2":"13C",
"IFS.spec.nmr.nucl.1":"1H",
"IFS.spec.nmr.expt.pulseprog":"hsqcetgp",
"IFS.spec.nmr.freq.nominal":500},
"listCount":1,
"list":[{"type":"unknown",
"len":14581367,
"ref":{"path":"22284726",
"localName":"compound_8.zip_compound_8_HSQC.zip_HSQC_.zip",
"value":"compound_8.zip|compound 8/HSQC.zip|HSQC/"}}]},
{"type":"NMRSpecData",
"subtype":"Unknown",
"name":"COSY.zip|COSY/",
"id":"33",
"urlIndex":0,
"path":"22284726",
"params":{"IFS.spec.nmr.param.expt":"COSY",
"IFS.spec.nmr.expt.dim":"2D",
"IFS.spec.nmr.nucl.1":"1H",
"IFS.spec.nmr.expt.pulseprog":"cosygpqf",
"IFS.spec.nmr.freq.nominal":500},
"listCount":1,
"list":[{"type":"unknown",
"len":3306301,
"ref":{"path":"22284726",
"localName":"compound_8.zip_compound_8_COSY.zip_COSY_.zip",
"value":"compound_8.zip|compound 8/COSY.zip|COSY/"}}]},
{"type":"NMRSpecData",
"subtype":"Unknown",
"name":"1H.zip|1H/",
"id":"34",
"urlIndex":1,
"path":"22284729",
"params":{"IFS.spec.nmr.param.expt":"1H",
"IFS.spec.nmr.expt.dim":"1D",
"IFS.spec.nmr.nucl.1":"1H",
"IFS.spec.nmr.expt.pulseprog":"zgpr",
"IFS.spec.nmr.freq.nominal":500},
"listCount":1,
"list":[{"type":"unknown",
"len":217195,
"ref":{"path":"22284729",
"localName":"Compound_s3.zip_Compound_s3_1H.zip_1H_.zip",
"value":"Compound_s3.zip|Compound s3/1H.zip|1H/"}}]},
{"type":"NMRSpecData",
"subtype":"Unknown",
"name":"13C.zip|13C/",
"id":"35",
"urlIndex":1,
"path":"22284729",
"params":{"IFS.spec.nmr.param.expt":"13C",
"IFS.spec.nmr.expt.dim":"1D",
"IFS.spec.nmr.nucl.1":"13C",
"IFS.spec.nmr.expt.pulseprog":"zgpg30",
"IFS.spec.nmr.freq.nominal":500},
"listCount":1,
"list":[{"type":"unknown",
"len":639848,
"ref":{"path":"22284729",
"localName":"Compound_s3.zip_Compound_s3_13C.zip_13C_.zip",
"value":"Compound_s3.zip|Compound s3/13C.zip|13C/"}}]},
{"type":"NMRSpecData",
"subtype":"Unknown",
"name":"1H.zip|1H/",
"id":"36",
"urlIndex":1,
"path":"22284729",
"params":{"IFS.spec.nmr.param.expt":"1H",
"IFS.spec.nmr.expt.dim":"1D",
"IFS.spec.nmr.nucl.1":"1H",
"IFS.spec.nmr.expt.pulseprog":"zg30",
"IFS.spec.nmr.freq.nominal":500},
"listCount":1,
"list":[{"type":"unknown",
"len":564874,
"ref":{"path":"22284729",
"localName":"Compound_11.zip_Compound_11_1H.zip_1H_.zip",
"value":"Compound_11.zip|Compound 11/1H.zip|1H/"}}]},
{"type":"NMRSpecData",
"subtype":"Unknown",
"name":"13C.zip|13C/",
"id":"37",
"urlIndex":1,
"path":"22284729",
"params":{"IFS.spec.nmr.param.expt":"13C",
"IFS.spec.nmr.expt.dim":"1D",
"IFS.spec.nmr.nucl.1":"13C",
"IFS.spec.nmr.expt.pulseprog":"zgpg30",
"IFS.spec.nmr.freq.nominal":500},
"listCount":1,
"list":[{"type":"unknown",
"len":641435,
"ref":{"path":"22284729",
"localName":"Compound_11.zip_Compound_11_13C.zip_13C_.zip",
"value":"Compound_11.zip|Compound 11/13C.zip|13C/"}}]},
{"type":"NMRSpecData",
"subtype":"Unknown",
"name":"HSQC.zip|HSQC/",
"id":"38",
"urlIndex":1,
"path":"22284729",
"params":{"IFS.spec.nmr.param.expt":"HSQC",
"IFS.spec.nmr.expt.dim":"2D",
"IFS.spec.nmr.nucl.2":"13C",
"IFS.spec.nmr.nucl.1":"1H",
"IFS.spec.nmr.expt.pulseprog":"hsqcetgp",
"IFS.spec.nmr.freq.nominal":500},
"listCount":1,
"list":[{"type":"unknown",
"len":14516494,
"ref":{"path":"22284729",
"localName":"Compound_11.zip_Compound_11_HSQC.zip_HSQC_.zip",
"value":"Compound_11.zip|Compound 11/HSQC.zip|HSQC/"}}]},
{"type":"NMRSpecData",
"subtype":"Unknown",
"name":"COSY.zip|COSY/",
"id":"39",
"urlIndex":1,
"path":"22284729",
"params":{"IFS.spec.nmr.param.expt":"COSY",
"IFS.spec.nmr.expt.dim":"2D",
"IFS.spec.nmr.nucl.1":"1H",
"IFS.spec.nmr.expt.pulseprog":"cosygpqf",
"IFS.spec.nmr.freq.nominal":500},
"listCount":1,
"list":[{"type":"unknown",
"len":3319385,
"ref":{"path":"22284729",
"localName":"Compound_11.zip_Compound_11_COSY.zip_COSY_.zip",
"value":"Compound_11.zip|Compound 11/COSY.zip|COSY/"}}]},
{"type":"NMRSpecData",
"subtype":"Unknown",
"name":"1H.zip|1H/",
"id":"40",
"urlIndex":1,
"path":"22284729",
"params":{"IFS.spec.nmr.param.expt":"1H",
"IFS.spec.nmr.expt.dim":"1D",
"IFS.spec.nmr.nucl.1":"1H",
"IFS.spec.nmr.expt.pulseprog":"zg30",
"IFS.spec.nmr.freq.nominal":500},
"listCount":1,
"list":[{"type":"unknown",
"len":577476,
"ref":{"path":"22284729",
"localName":"Compound_12.zip_Compound_12_1H.zip_1H_.zip",
"value":"Compound_12.zip|Compound 12/1H.zip|1H/"}}]},
{"type":"NMRSpecData",
"subtype":"Unknown",
"name":"13C.zip|13C/",
"id":"41",
"urlIndex":1,
"path":"22284729",
"params":{"IFS.spec.nmr.param.expt":"13C",
"IFS.spec.nmr.expt.dim":"1D",
"IFS.spec.nmr.nucl.1":"13C",
"IFS.spec.nmr.expt.pulseprog":"zgpg30",
"IFS.spec.nmr.freq.nominal":500},
"listCount":1,
"list":[{"type":"unknown",
"len":640452,
"ref":{"path":"22284729",
"localName":"Compound_12.zip_Compound_12_13C.zip_13C_.zip",
"value":"Compound_12.zip|Compound 12/13C.zip|13C/"}}]},
{"type":"NMRSpecData",
"subtype":"Unknown",
"name":"1H.zip|1H/",
"id":"42",
"urlIndex":1,
"path":"22284729",
"params":{"IFS.spec.nmr.param.expt":"1H",
"IFS.spec.nmr.expt.dim":"1D",
"IFS.spec.nmr.nucl.1":"1H",
"IFS.spec.nmr.expt.pulseprog":"zg30",
"IFS.spec.nmr.freq.nominal":500},
"listCount":1,
"list":[{"type":"unknown",
"len":571755,
"ref":{"path":"22284729",
"localName":"Compound_13.zip_Compound_13_1H.zip_1H_.zip",
"value":"Compound_13.zip|Compound 13/1H.zip|1H/"}}]},
{"type":"NMRSpecData",
"subtype":"Unknown",
"name":"13C.zip|13C/",
"id":"43",
"urlIndex":1,
"path":"22284729",
"params":{"IFS.spec.nmr.param.expt":"13C",
"IFS.spec.nmr.expt.dim":"1D",
"IFS.spec.nmr.nucl.1":"13C",
"IFS.spec.nmr.expt.pulseprog":"zgpg30",
"IFS.spec.nmr.freq.nominal":500},
"listCount":1,
"list":[{"type":"unknown",
"len":634732,
"ref":{"path":"22284729",
"localName":"Compound_13.zip_Compound_13_13C.zip_13C_.zip",
"value":"Compound_13.zip|Compound 13/13C.zip|13C/"}}]},
{"type":"NMRSpecData",
"subtype":"Unknown",
"name":"1H.zip|1H/",
"id":"44",
"urlIndex":1,
"path":"22284729",
"params":{"IFS.spec.nmr.param.expt":"1H",
"IFS.spec.nmr.expt.dim":"1D",
"IFS.spec.nmr.nucl.1":"1H",
"IFS.spec.nmr.expt.pulseprog":"zg30",
"IFS.spec.nmr.freq.nominal":500},
"listCount":1,
"list":[{"type":"unknown",
"len":553855,
"ref":{"path":"22284729",
"localName":"compound_s5.zip_compound_s5_1H.zip_1H_.zip",
"value":"compound_s5.zip|compound s5/1H.zip|1H/"}}]},
{"type":"NMRSpecData",
"subtype":"Unknown",
"name":"13C.zip|13C/",
"id":"45",
"urlIndex":1,
"path":"22284729",
"params":{"IFS.spec.nmr.param.expt":"13C",
"IFS.spec.nmr.expt.dim":"1D",
"IFS.spec.nmr.nucl.1":"13C",
"IFS.spec.nmr.expt.pulseprog":"zgpg30",
"IFS.spec.nmr.freq.nominal":500},
"listCount":1,
"list":[{"type":"unknown",
"len":637363,
"ref":{"path":"22284729",
"localName":"compound_s5.zip_compound_s5_13C.zip_13C_.zip",
"value":"compound_s5.zip|compound s5/13C.zip|13C/"}}]},
{"type":"NMRSpecData",
"subtype":"Unknown",
"name":"1H.zip|1H/",
"id":"46",
"urlIndex":1,
"path":"22284729",
"params":{"IFS.spec.nmr.param.expt":"1H",
"IFS.spec.nmr.expt.dim":"1D",
"IFS.spec.nmr.nucl.1":"1H",
"IFS.spec.nmr.expt.pulseprog":"zg30",
"IFS.spec.nmr.freq.nominal":500},
"listCount":1,
"list":[{"type":"unknown",
"len":547047,
"ref":{"path":"22284729",
"localName":"Compound_17.zip_Compound_17_1H.zip_1H_.zip",
"value":"Compound_17.zip|Compound 17/1H.zip|1H/"}}]},
{"type":"NMRSpecData",
"subtype":"Unknown",
"name":"13C.zip|13C/",
"id":"47",
"urlIndex":1,
"path":"22284729",
"params":{"IFS.spec.nmr.param.expt":"13C",
"IFS.spec.nmr.expt.dim":"1D",
"IFS.spec.nmr.nucl.1":"13C",
"IFS.spec.nmr.expt.pulseprog":"zgpg30",
"IFS.spec.nmr.freq.nominal":500},
"listCount":1,
"list":[{"type":"unknown",
"len":614701,
"ref":{"path":"22284729",
"localName":"Compound_17.zip_Compound_17_13C.zip_13C_.zip",
"value":"Compound_17.zip|Compound 17/13C.zip|13C/"}}]},
{"type":"NMRSpecData",
"subtype":"Unknown",
"name":"HSQC.zip|HSQC/",
"id":"48",
"urlIndex":1,
"path":"22284729",
"params":{"IFS.spec.nmr.param.expt":"HSQC",
"IFS.spec.nmr.expt.dim":"2D",
"IFS.spec.nmr.nucl.2":"13C",
"IFS.spec.nmr.nucl.1":"1H",
"IFS.spec.nmr.expt.pulseprog":"hsqcetgp",
"IFS.spec.nmr.freq.nominal":500},
"listCount":1,
"list":[{"type":"unknown",
"len":14237660,
"ref":{"path":"22284729",
"localName":"Compound_17.zip_Compound_17_HSQC.zip_HSQC_.zip",
"value":"Compound_17.zip|Compound 17/HSQC.zip|HSQC/"}}]},
{"type":"NMRSpecData",
"subtype":"Unknown",
"name":"COSY.zip|COSY/",
"id":"49",
"urlIndex":1,
"path":"22284729",
"params":{"IFS.spec.nmr.param.expt":"COSY",
"IFS.spec.nmr.expt.dim":"2D",
"IFS.spec.nmr.nucl.1":"1H",
"IFS.spec.nmr.expt.pulseprog":"cosygpqf",
"IFS.spec.nmr.freq.nominal":500},
"listCount":1,
"list":[{"type":"unknown",
"len":3225631,
"ref":{"path":"22284729",
"localName":"Compound_17.zip_Compound_17_COSY.zip_COSY_.zip",
"value":"Compound_17.zip|Compound 17/COSY.zip|COSY/"}}]},
{"type":"NMRSpecData",
"subtype":"Unknown",
"name":"1H.zip|1H/",
"id":"50",
"urlIndex":1,
"path":"22284729",
"params":{"IFS.spec.nmr.param.expt":"1H",
"IFS.spec.nmr.expt.dim":"1D",
"IFS.spec.nmr.nucl.1":"1H",
"IFS.spec.nmr.expt.pulseprog":"zg30",
"IFS.spec.nmr.freq.nominal":500},
"listCount":1,
"list":[{"type":"unknown",
"len":584996,
"ref":{"path":"22284729",
"localName":"Compound_16.zip_Compound_16_1H.zip_1H_.zip",
"value":"Compound_16.zip|Compound 16/1H.zip|1H/"}}]},
{"type":"NMRSpecData",
"subtype":"Unknown",
"name":"13C.zip|13C/",
"id":"51",
"urlIndex":1,
"path":"22284729",
"params":{"IFS.spec.nmr.param.expt":"13C",
"IFS.spec.nmr.expt.dim":"1D",
"IFS.spec.nmr.nucl.1":"13C",
"IFS.spec.nmr.expt.pulseprog":"zgpg",
"IFS.spec.nmr.freq.nominal":500},
"listCount":1,
"list":[{"type":"unknown",
"len":660178,
"ref":{"path":"22284729",
"localName":"Compound_16.zip_Compound_16_13C.zip_13C_.zip",
"value":"Compound_16.zip|Compound 16/13C.zip|13C/"}}]},
{"type":"NMRSpecData",
"subtype":"Unknown",
"name":"HSQC.zip|HSQC/",
"id":"52",
"urlIndex":1,
"path":"22284729",
"params":{"IFS.spec.nmr.param.expt":"HSQC",
"IFS.spec.nmr.expt.dim":"2D",
"IFS.spec.nmr.nucl.2":"13C",
"IFS.spec.nmr.nucl.1":"1H",
"IFS.spec.nmr.expt.pulseprog":"hsqcetgp",
"IFS.spec.nmr.freq.nominal":500},
"listCount":1,
"list":[{"type":"unknown",
"len":14875121,
"ref":{"path":"22284729",
"localName":"Compound_16.zip_Compound_16_HSQC.zip_HSQC_.zip",
"value":"Compound_16.zip|Compound 16/HSQC.zip|HSQC/"}}]},
{"type":"NMRSpecData",
"subtype":"Unknown",
"name":"COSY.zip|COSY/",
"id":"53",
"urlIndex":1,
"path":"22284729",
"params":{"IFS.spec.nmr.param.expt":"COSY",
"IFS.spec.nmr.expt.dim":"2D",
"IFS.spec.nmr.nucl.1":"1H",
"IFS.spec.nmr.expt.pulseprog":"cosygpqf",
"IFS.spec.nmr.freq.nominal":500},
"listCount":1,
"list":[{"type":"unknown",
"len":3492780,
"ref":{"path":"22284729",
"localName":"Compound_16.zip_Compound_16_COSY.zip_COSY_.zip",
"value":"Compound_16.zip|Compound 16/COSY.zip|COSY/"}}]},
{"type":"NMRSpecData",
"subtype":"Unknown",
"name":"1H.zip|1H/",
"id":"54",
"urlIndex":1,
"path":"22284729",
"params":{"IFS.spec.nmr.param.expt":"1H",
"IFS.spec.nmr.expt.dim":"1D",
"IFS.spec.nmr.nucl.1":"1H",
"IFS.spec.nmr.expt.pulseprog":"zg30",
"IFS.spec.nmr.freq.nominal":500},
"listCount":1,
"list":[{"type":"unknown",
"len":574418,
"ref":{"path":"22284729",
"localName":"Compound_14.zip_Compound_14_1H.zip_1H_.zip",
"value":"Compound_14.zip|Compound 14/1H.zip|1H/"}}]},
{"type":"NMRSpecData",
"subtype":"Unknown",
"name":"13C.zip|13C/",
"id":"55",
"urlIndex":1,
"path":"22284729",
"params":{"IFS.spec.nmr.param.expt":"13C",
"IFS.spec.nmr.expt.dim":"1D",
"IFS.spec.nmr.nucl.1":"13C",
"IFS.spec.nmr.expt.pulseprog":"zgpg30",
"IFS.spec.nmr.freq.nominal":500},
"listCount":1,
"list":[{"type":"unknown",
"len":633842,
"ref":{"path":"22284729",
"localName":"Compound_14.zip_Compound_14_13C.zip_13C_.zip",
"value":"Compound_14.zip|Compound 14/13C.zip|13C/"}}]},
{"type":"NMRSpecData",
"subtype":"Unknown",
"name":"1H.zip|1H/",
"id":"56",
"urlIndex":1,
"path":"22284729",
"params":{"IFS.spec.nmr.param.expt":"1H",
"IFS.spec.nmr.expt.dim":"1D",
"IFS.spec.nmr.nucl.1":"1H",
"IFS.spec.nmr.expt.pulseprog":"zg30",
"IFS.spec.nmr.freq.nominal":500},
"listCount":1,
"list":[{"type":"unknown",
"len":570825,
"ref":{"path":"22284729",
"localName":"Compound_15.zip_Compound_15_1H.zip_1H_.zip",
"value":"Compound_15.zip|Compound 15/1H.zip|1H/"}}]},
{"type":"NMRSpecData",
"subtype":"Unknown",
"name":"13C.zip|13C/",
"id":"57",
"urlIndex":1,
"path":"22284729",
"params":{"IFS.spec.nmr.param.expt":"13C",
"IFS.spec.nmr.expt.dim":"1D",
"IFS.spec.nmr.nucl.1":"13C",
"IFS.spec.nmr.expt.pulseprog":"zgpg30",
"IFS.spec.nmr.freq.nominal":500},
"listCount":1,
"list":[{"type":"unknown",
"len":642951,
"ref":{"path":"22284729",
"localName":"Compound_15.zip_Compound_15_13C.zip_13C_.zip",
"value":"Compound_15.zip|Compound 15/13C.zip|13C/"}}]},
{"type":"NMRSpecData",
"subtype":"Unknown",
"name":"HSQC.zip|HSQC/",
"id":"58",
"urlIndex":1,
"path":"22284729",
"params":{"IFS.spec.nmr.param.expt":"HSQC",
"IFS.spec.nmr.expt.dim":"2D",
"IFS.spec.nmr.nucl.2":"13C",
"IFS.spec.nmr.nucl.1":"1H",
"IFS.spec.nmr.expt.pulseprog":"hsqcetgp",
"IFS.spec.nmr.freq.nominal":500},
"listCount":1,
"list":[{"type":"unknown",
"len":14311687,
"ref":{"path":"22284729",
"localName":"Compound_15.zip_Compound_15_HSQC.zip_HSQC_.zip",
"value":"Compound_15.zip|Compound 15/HSQC.zip|HSQC/"}}]},
{"type":"NMRSpecData",
"subtype":"Unknown",
"name":"COSY.zip|COSY/",
"id":"59",
"urlIndex":1,
"path":"22284729",
"params":{"IFS.spec.nmr.param.expt":"COSY",
"IFS.spec.nmr.expt.dim":"2D",
"IFS.spec.nmr.nucl.1":"1H",
"IFS.spec.nmr.expt.pulseprog":"cosygpqf",
"IFS.spec.nmr.freq.nominal":500},
"listCount":1,
"list":[{"type":"unknown",
"len":3369657,
"ref":{"path":"22284729",
"localName":"Compound_15.zip_Compound_15_COSY.zip_COSY_.zip",
"value":"Compound_15.zip|Compound 15/COSY.zip|COSY/"}}]},
{"type":"NMRSpecData",
"subtype":"Unknown",
"name":"1H.zip|1H/",
"id":"60",
"urlIndex":1,
"path":"22284729",
"params":{"IFS.spec.nmr.param.expt":"1H",
"IFS.spec.nmr.expt.dim":"1D",
"IFS.spec.nmr.nucl.1":"1H",
"IFS.spec.nmr.expt.pulseprog":"zg30",
"IFS.spec.nmr.freq.nominal":500},
"listCount":1,
"list":[{"type":"unknown",
"len":559544,
"ref":{"path":"22284729",
"localName":"compound_s8.zip_compound_s8_1H.zip_1H_.zip",
"value":"compound_s8.zip|compound s8/1H.zip|1H/"}}]},
{"type":"NMRSpecData",
"subtype":"Unknown",
"name":"13C.zip|13C/",
"id":"61",
"urlIndex":1,
"path":"22284729",
"params":{"IFS.spec.nmr.param.expt":"13C",
"IFS.spec.nmr.expt.dim":"1D",
"IFS.spec.nmr.nucl.1":"13C",
"IFS.spec.nmr.expt.pulseprog":"zgpg30",
"IFS.spec.nmr.freq.nominal":500},
"listCount":1,
"list":[{"type":"unknown",
"len":617504,
"ref":{"path":"22284729",
"localName":"compound_s8.zip_compound_s8_13C.zip_13C_.zip",
"value":"compound_s8.zip|compound s8/13C.zip|13C/"}}]},
{"type":"NMRSpecData",
"subtype":"Unknown",
"name":"HSQC.zip|HSQC/",
"id":"62",
"urlIndex":1,
"path":"22284729",
"params":{"IFS.spec.nmr.param.expt":"HSQC",
"IFS.spec.nmr.expt.dim":"2D",
"IFS.spec.nmr.nucl.2":"13C",
"IFS.spec.nmr.nucl.1":"1H",
"IFS.spec.nmr.expt.pulseprog":"hsqcetgp",
"IFS.spec.nmr.freq.nominal":500},
"listCount":1,
"list":[{"type":"unknown",
"len":14211820,
"ref":{"path":"22284729",
"localName":"compound_s8.zip_compound_s8_HSQC.zip_HSQC_.zip",
"value":"compound_s8.zip|compound s8/HSQC.zip|HSQC/"}}]},
{"type":"NMRSpecData",
"subtype":"Unknown",
"name":"COSY.zip|COSY/",
"id":"63",
"urlIndex":1,
"path":"22284729",
"params":{"IFS.spec.nmr.param.expt":"COSY",
"IFS.spec.nmr.expt.dim":"2D",
"IFS.spec.nmr.nucl.1":"1H",
"IFS.spec.nmr.expt.pulseprog":"cosygpqf",
"IFS.spec.nmr.freq.nominal":500},
"listCount":1,
"list":[{"type":"unknown",
"len":3222296,
"ref":{"path":"22284729",
"localName":"compound_s8.zip_compound_s8_COSY.zip_COSY_.zip",
"value":"compound_s8.zip|compound s8/COSY.zip|COSY/"}}]}]},
"structureSpecDataCount":20,
"structureSpecData":{"type":"StructureSpecCollection",
"subtype":"Unknown",
"id":"5",
"listCount":20,
"list":[{"type":"StructureSpec",
"subtype":"Unknown",
"name":"Compound_10.zip|Compound 10/1H.zip|1H/",
"id":"0",
"struc":[0],
"data":[0,
1]},
{"type":"StructureSpec",
"subtype":"Unknown",
"name":"compound_5.zip|compound 5/1H.zip|1H/",
"id":"1",
"struc":[1],
"data":[2,
3,
4,
5]},
{"type":"StructureSpec",
"subtype":"Unknown",
"name":"Compound_4.zip|Compound 4/1H.zip|1H/",
"id":"2",
"struc":[2],
"data":[6,
7,
8,
9]},
{"type":"StructureSpec",
"subtype":"Unknown",
"name":"compound_6.zip|compound 6/1H.zip|1H/",
"id":"3",
"struc":[3],
"data":[10,
11,
12,
13]},
{"type":"StructureSpec",
"subtype":"Unknown",
"name":"COmpound_7.zip|COmpound 7/1H.zip|1H/",
"id":"4",
"struc":[4],
"data":[14,
15,
16,
17]},
{"type":"StructureSpec",
"subtype":"Unknown",
"name":"Compound_3.zip|Compound 3/1H.zip|1H/",
"id":"5",
"struc":[5],
"data":[18,
19,
20,
21]},
{"type":"StructureSpec",
"subtype":"Unknown",
"name":"compound_2.zip|compound 2/1H.zip|1H/",
"id":"6",
"struc":[6],
"data":[22,
23]},
{"type":"StructureSpec",
"subtype":"Unknown",
"name":"Compound_1.zip|Compound 1/1H.zip|1H/",
"id":"7",
"struc":[7],
"data":[24,
25,
26,
27]},
{"type":"StructureSpec",
"subtype":"Unknown",
"name":"compound_9.zip|compound 9/1H.zip|1H/",
"id":"8",
"struc":[8],
"data":[28,
29]},
{"type":"StructureSpec",
"subtype":"Unknown",
"name":"compound_8.zip|compound 8/1H.zip|1H/",
"id":"9",
"struc":[9],
"data":[30,
31,
32,
33]},
{"type":"StructureSpec",
"subtype":"Unknown",
"name":"Compound_s3.zip|Compound s3/1H.zip|1H/",
"id":"10",
"struc":[10],
"data":[34,
35]},
{"type":"StructureSpec",
"subtype":"Unknown",
"name":"Compound_11.zip|Compound 11/1H.zip|1H/",
"id":"11",
"struc":[11],
"data":[36,
37,
38,
39]},
{"type":"StructureSpec",
"subtype":"Unknown",
"name":"Compound_12.zip|Compound 12/1H.zip|1H/",
"id":"12",
"struc":[12],
"data":[40,
41]},
{"type":"StructureSpec",
"subtype":"Unknown",
"name":"Compound_13.zip|Compound 13/1H.zip|1H/",
"id":"13",
"struc":[13],
"data":[42,
43]},
{"type":"StructureSpec",
"subtype":"Unknown",
"name":"compound_s5.zip|compound s5/1H.zip|1H/",
"id":"14",
"struc":[14],
"data":[44,
45]},
{"type":"StructureSpec",
"subtype":"Unknown",
"name":"Compound_17.zip|Compound 17/1H.zip|1H/",
"id":"15",
"struc":[15],
"data":[46,
47,
48,
49]},
{"type":"StructureSpec",
"subtype":"Unknown",
"name":"Compound_16.zip|Compound 16/1H.zip|1H/",
"id":"16",
"struc":[16],
"data":[50,
51,
52,
53]},
{"type":"StructureSpec",
"subtype":"Unknown",
"name":"Compound_14.zip|Compound 14/1H.zip|1H/",
"id":"17",
"struc":[17],
"data":[54,
55]},
{"type":"StructureSpec",
"subtype":"Unknown",
"name":"Compound_15.zip|Compound 15/1H.zip|1H/",
"id":"18",
"struc":[18],
"data":[56,
57,
58,
59]},
{"type":"StructureSpec",
"subtype":"Unknown",
"name":"compound_s8.zip|compound s8/1H.zip|1H/",
"id":"19",
"struc":[19],
"data":[60,
61,
62,
63]}]}}}